{
  "expenses": [
    {
      "id": 0.9313621720190981,
      "dateAdded": "2023-06-10T04:00:00.000Z",
      "category": "grocery",
      "description": "foo foo",
      "amount": 40
    },
    {
      "id": 0.27057122017025703,
      "dateAdded": "2023-06-20T04:00:00.000Z",
      "category": "gas",
      "description": "foo foo",
      "amount": 50
    },
    {
      "id": 0.19971020148937524,
      "dateAdded": "2023-07-10T04:00:00.000Z",
      "category": "grocery",
      "description": "foo foo",
      "amount": 70
    },
    {
      "id": 0.034153401317661425,
      "dateAdded": "2023-07-20T04:00:00.000Z",
      "category": "gas",
      "description": "foo foo",
      "amount": 30
    },
    {
      "id": 0.9822040969993899,
      "dateAdded": "2023-07-21T16:12:00.877Z",
      "category": "gas",
      "description": "",
      "amount": 123
    },
    {
      "id": 0.6071899434705497,
      "dateAdded": "7/21/2023, 12:46:01 PM",
      "category": "grocery",
      "description": "",
      "amount": 350
    },
    {
      "id": 0.03528397279370177,
      "dateAdded": "7/21/2023, 1:05:33 PM",
      "category": "gas",
      "description": "",
      "amount": 123
    },
    {
      "id": 0.9589057781793342,
      "dateAdded": "7/21/2023, 1:11:28 PM",
      "category": "gas",
      "description": "",
      "amount": 40
    },
    {
      "id": 0.908037704143547,
      "dateAdded": "7/21/2023, 1:12:48 PM",
      "category": "movies",
      "description": "",
      "amount": 50
    }
  ]
}